rest_framework_sso/__init__.py
rest_framework_sso/authentication.py
rest_framework_sso/claims.py
rest_framework_sso/keys.py
rest_framework_sso/models.py
rest_framework_sso/querysets.py
rest_framework_sso/serializers.py
rest_framework_sso/settings.py
rest_framework_sso/utils.py
rest_framework_sso/views.py
rest_framework_sso/migrations/0001_initial.py
rest_framework_sso/migrations/0002_sessiontoken_last_used_at.py
rest_framework_sso/migrations/0003_sessiontoken_client_id.py
rest_framework_sso/migrations/0004_sessiontoken_created_by.py
rest_framework_sso/migrations/0005_sessiontoken_version.py
rest_framework_sso/migrations/__init__.py
djangorestframework_sso-0.5.2.dist-info/LICENSE
djangorestframework_sso-0.5.2.dist-info/METADATA
djangorestframework_sso-0.5.2.dist-info/WHEEL
djangorestframework_sso-0.5.2.dist-info/top_level.txt
djangorestframework_sso-0.5.2.dist-info/RECORD
