Metadata-Version: 2.1
Name: djangorestframework-sso
Version: 0.5.2
Summary: Single sign-on extension to the Django REST Framework.
Home-page: https://github.com/namespace-ee/django-rest-framework-sso
Author: Lenno Nagel
Author-email: lenno@namespace.ee
License: MIT License
Classifier: Development Status :: 5 - Production/Stable
Classifier: Environment :: Web Environment
Classifier: Framework :: Django
Classifier: Intended Audience :: Developers
Classifier: License :: OSI Approved :: MIT License
Classifier: Operating System :: OS Independent
Classifier: Programming Language :: Python
Classifier: Programming Language :: Python :: 3.10
Classifier: Programming Language :: Python :: 3.11
Classifier: Programming Language :: Python :: 3.12
Classifier: Topic :: Internet :: WWW/HTTP
Classifier: Topic :: Internet :: WWW/HTTP :: Session
Classifier: Topic :: Software Development :: Libraries :: Python Modules
License-File: LICENSE
Requires-Dist: djangorestframework
Requires-Dist: cryptography
Requires-Dist: pem
Requires-Dist: PyJWT>=2.0
